{
  "name": "alien-cotg",
  "title": "Alien - Chariot of the Gods",
  "description": "",
  "version": "1.0.0",
  "minimumCoreVersion": "0.0.0",
  "compatibleCoreVersion": "1.0.0",
  "scripts": [],
  "esmodules": [],
  "styles": [],
  "packs": [
    {
      "label": "Talents",
      "entity": "Item",
      "name": "talents",
      "path": "packs/talents.db",
      "system": "alienrpg",
      "package": "world",
      "absPath": "C:\\Users\\Maho\\AppData\\Local\\FoundryVTT\\Data\\worlds\\alien-cotg\\packs\\talents.db"
    },
    {
      "label": "Alien Creature Tables",
      "entity": "RollTable",
      "name": "alien-creature-tables",
      "path": "packs/alien-creature-tables.db",
      "system": "alienrpg",
      "package": "world",
      "absPath": "C:\\Users\\Maho\\AppData\\Local\\FoundryVTT\\Data\\worlds\\alien-cotg\\packs\\alien-creature-tables.db"
    },
    {
      "label": "Neomorphs",
      "entity": "Actor",
      "name": "neomorphs",
      "path": "packs/neomorphs.db",
      "system": "alienrpg",
      "package": "world",
      "absPath": "C:\\Users\\Maho\\AppData\\Local\\FoundryVTT\\Data\\worlds\\alien-cotg\\packs\\neomorphs.db"
    },
    {
      "label": "Xenomorph XX121",
      "entity": "Actor",
      "name": "xenomorph-xx121",
      "path": "packs/xenomorph-xx121.db",
      "system": "alienrpg",
      "package": "world",
      "absPath": "C:\\Users\\Maho\\AppData\\Local\\FoundryVTT\\Data\\worlds\\alien-cotg\\packs\\xenomorph-xx121.db"
    },
    {
      "label": "Abominations",
      "entity": "Actor",
      "name": "abominations",
      "path": "packs/abominations.db",
      "system": "alienrpg",
      "package": "world",
      "absPath": "C:\\Users\\Maho\\AppData\\Local\\FoundryVTT\\Data\\worlds\\alien-cotg\\packs\\abominations.db"
    },
    {
      "label": "COTG - PC",
      "entity": "Actor",
      "name": "cotg-pc",
      "path": "packs/cotg-pc.db",
      "system": "alienrpg",
      "package": "world",
      "absPath": "C:\\Users\\Maho\\AppData\\Local\\FoundryVTT\\Data\\worlds\\alien-cotg\\packs\\cotg-pc.db"
    },
    {
      "label": "COTG - NPC",
      "entity": "Actor",
      "name": "cotg-npc",
      "path": "packs/cotg-npc.db",
      "system": "alienrpg",
      "package": "world",
      "absPath": "C:\\Users\\Maho\\AppData\\Local\\FoundryVTT\\Data\\worlds\\alien-cotg\\packs\\cotg-npc.db"
    },
    {
      "label": "COTG - Scenes",
      "entity": "Scene",
      "name": "cotg-scenes",
      "path": "packs/cotg-scenes.db",
      "system": "alienrpg",
      "package": "world",
      "absPath": "C:\\Users\\Maho\\AppData\\Local\\FoundryVTT\\Data\\worlds\\alien-cotg\\packs\\cotg-scenes.db"
    },
    {
      "label": "Skill-Stunts",
      "entity": "Item",
      "name": "skill-stunts",
      "path": "packs/skill-stunts.db",
      "system": "alienrpg",
      "package": "world",
      "absPath": "C:\\Users\\Maho\\AppData\\Local\\FoundryVTT\\Data\\worlds\\alien-cotg\\packs\\skill-stunts.db"
    },
    {
      "label": "Rules",
      "entity": "JournalEntry",
      "name": "rules",
      "path": "packs/rules.db",
      "system": "alienrpg",
      "package": "world",
      "absPath": "C:\\Users\\Maho\\AppData\\Local\\FoundryVTT\\Data\\worlds\\alien-cotg\\packs\\rules.db"
    },
    {
      "label": "Alien Mother Tables",
      "entity": "RollTable",
      "name": "alien-mother-tables",
      "path": "packs/alien-mother-tables.db",
      "system": "alienrpg",
      "package": "world",
      "absPath": "C:\\Users\\Maho\\AppData\\Local\\FoundryVTT\\Data\\worlds\\alien-cotg\\packs\\alien-mother-tables.db"
    },
    {
      "label": "COTG - Cinematic Scenario",
      "entity": "JournalEntry",
      "name": "cotg-cinematic-scenario",
      "path": "packs/cotg-cinematic-scenario.db",
      "system": "alienrpg",
      "package": "world",
      "absPath": "C:\\Users\\Maho\\AppData\\Local\\FoundryVTT\\Data\\worlds\\alien-cotg\\packs\\cotg-cinematic-scenario.db"
    },
    {
      "label": "Armors",
      "entity": "Item",
      "name": "armors",
      "path": "packs/armors.db",
      "system": "alienrpg",
      "package": "world",
      "absPath": "C:\\Users\\Maho\\AppData\\Local\\FoundryVTT\\Data\\worlds\\alien-cotg\\packs\\armors.db"
    },
    {
      "label": "Diagnostics & Displays",
      "entity": "Item",
      "name": "diagnostics-and-displays",
      "path": "packs/diagnostics-and-displays.db",
      "system": "alienrpg",
      "package": "world",
      "absPath": "C:\\Users\\Maho\\AppData\\Local\\FoundryVTT\\Data\\worlds\\alien-cotg\\packs\\diagnostics-and-displays.db"
    },
    {
      "label": "Medical Supplies",
      "entity": "Item",
      "name": "medical-supplies",
      "path": "packs/medical-supplies.db",
      "system": "alienrpg",
      "package": "world",
      "absPath": "C:\\Users\\Maho\\AppData\\Local\\FoundryVTT\\Data\\worlds\\alien-cotg\\packs\\medical-supplies.db"
    },
    {
      "label": "Weapons",
      "entity": "Item",
      "name": "weapons",
      "path": "packs/weapons.db",
      "system": "alienrpg",
      "package": "world",
      "absPath": "C:\\Users\\Maho\\AppData\\Local\\FoundryVTT\\Data\\worlds\\alien-cotg\\packs\\weapons.db"
    },
    {
      "label": "Vehicles",
      "entity": "Actor",
      "name": "vehicles",
      "path": "packs/vehicles.db",
      "system": "alienrpg",
      "package": "world",
      "absPath": "C:\\Users\\Maho\\AppData\\Local\\FoundryVTT\\Data\\worlds\\alien-cotg\\packs\\vehicles.db"
    },
    {
      "label": "Pharmaceuticals",
      "entity": "Item",
      "name": "pharmaceuticals",
      "path": "packs/pharmaceuticals.db",
      "system": "alienrpg",
      "package": "world",
      "absPath": "C:\\Users\\Maho\\AppData\\Local\\FoundryVTT\\Data\\worlds\\alien-cotg\\packs\\pharmaceuticals.db"
    }
  ],
  "languages": [],
  "authors": [],
  "keywords": [],
  "socket": false,
  "url": "",
  "manifest": "",
  "download": "",
  "license": "",
  "readme": "",
  "bugs": "",
  "changelog": "",
  "background": "Alien-COTG.png",
  "system": "alienrpg",
  "coreVersion": "0.7.9",
  "systemVersion": "1.2.20",
  "nextSession": "",
  "availability": 1,
  "unavailable": false,
  "id": "alien-cotg"
}